stormlock/__init__.py
stormlock/_backend_config.py
stormlock/backend.py
stormlock/backends/__init__.py
stormlock/backends/dynamodb.py
stormlock/backends/etcd/__init__.py
stormlock/backends/etcd/proto/kv.proto
stormlock/backends/etcd/proto/kv_pb2.py
stormlock/backends/etcd/proto/kv_pb2.pyi
stormlock/backends/etcd/proto/rpc.proto
stormlock/backends/etcd/proto/rpc_pb2.py
stormlock/backends/etcd/proto/rpc_pb2.pyi
stormlock/backends/etcd/proto/rpc_pb2_grpc.py
stormlock/backends/mysql.py
stormlock/backends/postgresql.py
stormlock/backends/redis.py
stormlock/cli.py
stormlock/lock.py
stormlock-0.4.1.dist-info/LICENSE
stormlock-0.4.1.dist-info/METADATA
stormlock-0.4.1.dist-info/WHEEL
stormlock-0.4.1.dist-info/entry_points.txt
stormlock-0.4.1.dist-info/RECORD
