Metadata-Version: 2.1
Name: stormlock
Version: 0.4.1
Summary: Simple distributed lock with support for multiple backends
Home-page: https://github.com/tmccombs/stormlock
Keywords: lock,cli
Author: Thayne McCombs
Author-email: astrothayne@gmail.com
Requires-Python: >=3.9,<4.0
Classifier: Programming Language :: Python :: 3
Classifier: Programming Language :: Python :: 3.9
Classifier: Programming Language :: Python :: 3.10
Classifier: Programming Language :: Python :: 3.11
Provides-Extra: dynamodb
Provides-Extra: etcd
Provides-Extra: mysql
Provides-Extra: postgresql
Provides-Extra: redis
Requires-Dist: boto3 (>=1.26.100,<2.0.0) ; extra == "dynamodb"
Requires-Dist: grpcio (>=1.57,<2.0) ; extra == "etcd"
Requires-Dist: mysql-connector-python (>=8.1.0,<10.0) ; extra == "mysql"
Requires-Dist: protobuf (>=4.21,<5.0) ; extra == "etcd"
Requires-Dist: psycopg[c] (>=3.1.8,<4.0.0) ; extra == "postgresql"
Requires-Dist: redis (>=5.0.0,<6.0.0) ; extra == "redis"
Project-URL: Repository, https://github.com/tmccombs/stormlock
